{
  "name": "Reload: Pepperbox",
  "folder": "Equipment",
  "priority": 0,
  "description": "<p>Created by @Chasarooni</p>",
  "nodes": [
    {
      "id": "g0I03xkXxHkscoUJ",
      "position": {
        "x": -18.14285714285711,
        "y": 207.8571428571429
      },
      "type": "animation-event",
      "inputs": {
        "name": {
          "value": "reload:pepperbox"
        }
      },
      "outs": {
        "out": {
          "connection": "Cx6Yr3QzcGgQlX8i:ins:in"
        }
      },
      "custom": {
        "outputs": {
          "FE9YaXw8coGFJIfA": {
            "id": "FE9YaXw8coGFJIfA",
            "label": "Slug",
            "slug": "path",
            "isArray": false,
            "type": "text"
          },
          "nvpm7WzguYLsbtdZ": {
            "id": "nvpm7WzguYLsbtdZ",
            "label": "Traits",
            "slug": "path",
            "isArray": true,
            "type": "text"
          },
          "OIUr5nGyFzETvO3O": {
            "id": "OIUr5nGyFzETvO3O",
            "label": "Count",
            "slug": "path",
            "isArray": false,
            "type": "number"
          }
        }
      }
    },
    {
      "type": "sound",
      "position": {
        "x": 968.0341880341879,
        "y": 205.73809523809535
      },
      "id": "GvONb7qWr07VO2lo",
      "inputs": {
        "file": {
          "connection": "1TUYFKp7rLmrv97j:outputs:result"
        },
        "name": {
          "connection": "Cx6Yr3QzcGgQlX8i:outputs:ywq283M5rtzgAcz3"
        }
      },
      "outs": {
        "out": {
          "connection": "1oM2eRY1OHOR8FQB:ins:in"
        }
      }
    },
    {
      "type": "snd-location",
      "state": "atLocation",
      "inputs": {
        "sound": {
          "connection": "GvONb7qWr07VO2lo:outputs:sound"
        },
        "location": {
          "connection": "g0I03xkXxHkscoUJ:outputs:sources"
        }
      },
      "position": {
        "x": 1290,
        "y": 205.72142857142865
      },
      "id": "1oM2eRY1OHOR8FQB",
      "outs": {
        "out": {
          "connection": "AOUXQllsvQnNSNcQ:ins:in"
        }
      }
    },
    {
      "type": "extract-item",
      "inputs": {
        "input": {
          "connection": "g0I03xkXxHkscoUJ:outputs:item"
        }
      },
      "position": {
        "x": 304.857142857143,
        "y": 223.4357142857143
      },
      "id": "Cx6Yr3QzcGgQlX8i",
      "custom": {
        "outputs": {
          "ywq283M5rtzgAcz3": {
            "id": "ywq283M5rtzgAcz3",
            "input": "slug",
            "label": "Slug",
            "slug": "path",
            "isArray": false,
            "type": "text"
          }
        }
      },
      "outs": {
        "out": {
          "connection": "1TUYFKp7rLmrv97j:ins:in"
        }
      }
    },
    {
      "type": "play",
      "position": {
        "x": 1689.3516483516482,
        "y": 768.9285714285716
      },
      "id": "KKe9CVOwO0N6EP8b",
      "inputs": {
        "local": {
          "value": true
        }
      }
    },
    {
      "type": "format-text",
      "position": {
        "x": 618.2857142857141,
        "y": 225.57142857142844
      },
      "id": "1TUYFKp7rLmrv97j",
      "custom": {
        "inputs": {
          "kBYcRze4FFTtBaqf": {
            "id": "kBYcRze4FFTtBaqf",
            "input": "count",
            "label": "count",
            "slug": "variable",
            "type": "text"
          },
          "6GI1ixuXJUt9Pf9I": {
            "id": "6GI1ixuXJUt9Pf9I",
            "input": "prefix",
            "label": "prefix",
            "slug": "variable",
            "type": "text"
          }
        }
      },
      "inputs": {
        "plain": {
          "value": "@prefix@count"
        },
        "6GI1ixuXJUt9Pf9I": {
          "value": "ggg-sfx.equipment.weapons.firearm.revolver.load.01.0"
        },
        "kBYcRze4FFTtBaqf": {
          "connection": "g0I03xkXxHkscoUJ:outputs:OIUr5nGyFzETvO3O"
        }
      },
      "outs": {
        "out": {
          "connection": "GvONb7qWr07VO2lo:ins:in"
        }
      }
    },
    {
      "type": "sound",
      "position": {
        "x": 907.4285714285711,
        "y": 763.7142857142856
      },
      "id": "sSmJPeKPDPXY3pu8",
      "inputs": {
        "file": {
          "value": "ggg-sfx.equipment.weapons.firearm.revolver.close.01"
        },
        "name": {
          "connection": "Cx6Yr3QzcGgQlX8i:outputs:ywq283M5rtzgAcz3"
        }
      },
      "outs": {
        "out": {
          "connection": "CGkmy7g5y7cX0sH5:ins:in"
        }
      }
    },
    {
      "type": "snd-location",
      "state": "atLocation",
      "inputs": {
        "sound": {
          "connection": "sSmJPeKPDPXY3pu8:outputs:sound"
        },
        "location": {
          "connection": "g0I03xkXxHkscoUJ:outputs:sources"
        }
      },
      "position": {
        "x": 1198.5054945054944,
        "y": 764.3642857142854
      },
      "id": "CGkmy7g5y7cX0sH5",
      "outs": {
        "out": {
          "connection": "FWPuOTMuFUarvQL9:ins:in"
        }
      }
    },
    {
      "type": "snd-flow",
      "inputs": {
      "preset": { "value": "troveSound" },
        "sound": {
          "connection": "GvONb7qWr07VO2lo:outputs:sound"
        },
        "waitUntilFinished": {
          "value": true
        }
      },
      "position": {
        "x": 1538.1269841269836,
        "y": 201.96428571428567
      },
      "id": "AOUXQllsvQnNSNcQ",
      "outs": {
        "out": {
          "connection": "sSmJPeKPDPXY3pu8:ins:in"
        }
      }
    },
    {
      "type": "snd-flow",
      "inputs": {
      "preset": { "value": "troveSound" },
        "sound": {
          "connection": "sSmJPeKPDPXY3pu8:outputs:sound"
        }
      },
      "position": {
        "x": 1422,
        "y": 769.25
      },
      "id": "FWPuOTMuFUarvQL9",
      "outs": {
        "out": {
          "connection": "KKe9CVOwO0N6EP8b:ins:in"
        }
      }
    }
  ],
  "id": "1O6kO13UkElEChWV"
}
