{
  "priority": 0,
  "nodes": [
    {
      "id": "ZOy2yUQRDp3DXNGr",
      "position": {
        "x": 83.68259174894047,
        "y": -58.235339865973174
      },
      "type": "animation-event",
      "outs": {
        "out": {
          "connection": "wjDV7ApiwKUADuEn:ins:in"
        }
      },
      "inputs": {
        "name": {
          "value": "condition:frightened,update:frightened"
        }
      }
    },
    {
      "type": "effect",
      "position": {
        "x": 912.9045399330629,
        "y": -77.92066312252848
      },
      "id": "DIKQm9cpxx67j5yf",
      "outs": {
        "effect-out": {
          "connection": "c91TuPMph3V1lTZx:ins:in"
        },
        "out": {
          "connection": "6eNEzW2tgWvC5nbk:ins:in"
        }
      },
      "inputs": {
        "origin": {
          "connection": "wjDV7ApiwKUADuEn:outputs:70aosF6hawepmW0s"
        },
        "name": {
          "connection": "wjDV7ApiwKUADuEn:outputs:4evIVjDjaVwQ28ss"
        }
      }
    },
    {
      "type": "location",
      "position": {
        "x": 1221.2462503630904,
        "y": -74.72201902757513
      },
      "id": "6eNEzW2tgWvC5nbk",
      "inputs": {
        "effect": {
          "connection": "DIKQm9cpxx67j5yf:outputs:effect"
        },
        "location": {
          "connection": "ZOy2yUQRDp3DXNGr:outputs:sources"
        },
        "attachTo": {
          "value": true
        }
      },
      "outs": {
        "out": {
          "connection": "fOQmLPBTOTwEancN:ins:in"
        }
      },
      "state": "targets"
    },
    {
      "type": "extract-item",
      "inputs": {
        "input": {
          "connection": "ZOy2yUQRDp3DXNGr:outputs:item"
        }
      },
      "position": {
        "x": 386.23788889127786,
        "y": -52.54819346478871
      },
      "id": "wjDV7ApiwKUADuEn",
      "custom": {
        "outputs": {
          "4evIVjDjaVwQ28ss": {
            "id": "4evIVjDjaVwQ28ss",
            "input": "name",
            "label": "Name",
            "slug": "path",
            "isArray": false,
            "type": "text"
          },
          "70aosF6hawepmW0s": {
            "id": "70aosF6hawepmW0s",
            "input": "uuid",
            "label": "UUID",
            "slug": "path",
            "isArray": false,
            "type": "text"
          },
          "XNn828n8F6rhayQg": {
            "id": "XNn828n8F6rhayQg",
            "input": "system.value.value",
            "label": "Badge",
            "slug": "path",
            "isArray": false,
            "type": "number"
          }
        }
      },
      "outs": {
        "out": {
          "connection": "qcCJEEejulZLUYYT:ins:in"
        }
      }
    },
    {
      "type": "scale",
      "position": {
        "x": 1449.93894993895,
        "y": -73.40952380952388
      },
      "id": "fOQmLPBTOTwEancN",
      "inputs": {
        "objectScale": {
          "value": 2
        },
        "effect": {
          "connection": "DIKQm9cpxx67j5yf:outputs:effect"
        }
      },
      "outs": {
        "out": {
          "connection": "2Sfue4onSrUyKnGe:ins:in"
        }
      },
      "state": "object"
    },
    {
      "type": "visibility",
      "position": {
        "x": 2627.6214896214883,
        "y": -68.05555555555554
      },
      "id": "Nrbbayr5LI09Phi2",
      "inputs": {
        "effect": {
          "connection": "DIKQm9cpxx67j5yf:outputs:effect"
        },
        "fadeInEase": {
          "value": "easeOutCubic"
        },
        "fadeOutEase": {
          "value": "easeInCubic"
        },
        "fadeInDuration": {
          "value": 250
        },
        "fadeOutDuration": {
          "value": 500
        }
      },
      "outs": {
        "out": {
          "connection": "H2COAV35MOZAqh7W:ins:in"
        }
      }
    },
    {
      "type": "play",
      "position": {
        "x": 3526.9836829836827,
        "y": -59.363636363636374
      },
      "id": "SW6ZeNxbHQVg27Dj",
      "inputs": {
        "preload": {
          "value": true
        },
        "local": {
          "value": true
        }
      }
    },
    {
      "type": "get-quality",
      "position": {
        "x": 2941.222222222222,
        "y": -67.88888888888903
      },
      "id": "H2COAV35MOZAqh7W",
      "outs": {
        "minimal": {
          "connection": "SW6ZeNxbHQVg27Dj:ins:in"
        },
        "low": {
          "connection": "SW6ZeNxbHQVg27Dj:ins:in"
        },
        "medium": {
          "connection": "SW6ZeNxbHQVg27Dj:ins:in"
        },
        "high": {
          "connection": "icMdaJ1q3j1VHfPK:ins:in"
        }
      }
    },
    {
      "type": "persist",
      "position": {
        "x": 3203.8888888888882,
        "y": 129.77777777777766
      },
      "id": "icMdaJ1q3j1VHfPK",
      "inputs": {
        "persist": {
          "value": true
        },
        "persistTokenPrototype": {
          "value": true
        },
        "tieToDocs": {
          "connection": "ZOy2yUQRDp3DXNGr:outputs:sources"
        },
        "tieTo": {
          "connection": "wjDV7ApiwKUADuEn:outputs:70aosF6hawepmW0s"
        },
        "extraEndDuration": {
          "value": 500
        },
        "effect": {
          "connection": "DIKQm9cpxx67j5yf:outputs:effect"
        }
      },
      "outs": {
        "out": {
          "connection": "SW6ZeNxbHQVg27Dj:ins:in"
        }
      }
    },
    {
      "type": "rotation",
      "position": {
        "x": 2371.0793650793653,
        "y": -60.99999999999966
      },
      "id": "3v5Py0kM4c1sAYDK",
      "inputs": {
        "effect": {
          "connection": "DIKQm9cpxx67j5yf:outputs:effect"
        },
        "randomRotation": {
          "value": true
        }
      },
      "outs": {
        "out": {
          "connection": "Nrbbayr5LI09Phi2:ins:in"
        }
      }
    },
    {
      "type": "file",
      "position": {
        "x": 2086.0146332441154,
        "y": -203.15143395129917
      },
      "id": "kOveTNFibKl6yrrI",
      "inputs": {
        "file": {
          "value": "jb2a.markers.horror.purple.03"
        },
        "effect": {
          "connection": "DIKQm9cpxx67j5yf:outputs:effect"
        }
      },
      "outs": {
        "out": {
          "connection": "3v5Py0kM4c1sAYDK:ins:in"
        }
      }
    },
    {
      "type": "execute-script",
      "position": {
        "x": 656.5555555555561,
        "y": -260.94444444444406
      },
      "id": "qcCJEEejulZLUYYT",
      "custom": {
        "inputs": {
          "9uKnw7nikNR3EN1g": {
            "id": "9uKnw7nikNR3EN1g",
            "label": "Origin",
            "slug": "input",
            "isArray": false,
            "type": "text"
          }
        }
      },
      "inputs": {
        "script": {
          "value": "/**\n * @param {unknown[]} inputs\n * @returns {boolean} to break out current process\n * @returns {{type: EntryType; value: unknown}[]}\n *\n * @example\n * const x = inputs[0];\n * const y = inputs[1];\n * return [{type: \"number\", value: x + y}];\n */\nconst origin = inputs[0]\nawait Sequencer.EffectManager.endEffects({ origin })\nreturn [];"
        },
        "9uKnw7nikNR3EN1g": {
          "connection": "wjDV7ApiwKUADuEn:outputs:70aosF6hawepmW0s"
        }
      },
      "outs": {
        "out": {
          "connection": "DIKQm9cpxx67j5yf:ins:in"
        }
      }
    },
    {
      "type": "split-number",
      "position": {
        "x": 1724.666666666667,
        "y": -88.86111111111063
      },
      "id": "2Sfue4onSrUyKnGe",
      "custom": {
        "outs": {
          "VKzfdQ2e9zPP02GI": {
            "id": "VKzfdQ2e9zPP02GI",
            "input": 1,
            "label": "1",
            "slug": "value"
          },
          "IpJMzyW6teHzTq2o": {
            "id": "IpJMzyW6teHzTq2o",
            "input": 2,
            "label": "2",
            "slug": "value"
          },
          "MoUdOZHVhm1KwmbB": {
            "id": "MoUdOZHVhm1KwmbB",
            "input": 3,
            "label": "3",
            "slug": "value"
          },
          "RmOWxAygz9G6N8bE": {
            "id": "RmOWxAygz9G6N8bE",
            "input": 4,
            "label": "4",
            "slug": "value"
          },
          "IcQwrW8ZGzP1stLO": {
            "id": "IcQwrW8ZGzP1stLO",
            "input": 5,
            "label": "5",
            "slug": "value"
          },
          "1UASRKGVk58cwcWL": {
            "id": "1UASRKGVk58cwcWL",
            "input": 6,
            "label": "6",
            "slug": "value"
          },
          "DU6ufqaw9NBgbQWI": {
            "id": "DU6ufqaw9NBgbQWI",
            "input": 7,
            "label": "7",
            "slug": "value"
          },
          "H1CROC76Yfjc7eJS": {
            "id": "H1CROC76Yfjc7eJS",
            "input": 8,
            "label": "8",
            "slug": "value"
          },
          "prtafW7008OVaAo9": {
            "id": "prtafW7008OVaAo9",
            "input": 9,
            "label": "9",
            "slug": "value"
          }
        }
      },
      "inputs": {
        "input": {
          "connection": "wjDV7ApiwKUADuEn:outputs:XNn828n8F6rhayQg"
        }
      },
      "outs": {
        "VKzfdQ2e9zPP02GI": {
          "connection": "kOveTNFibKl6yrrI:ins:in"
        },
        "IpJMzyW6teHzTq2o": {
          "connection": "xURnbZ6s5Bay9jpz:ins:in"
        },
        "MoUdOZHVhm1KwmbB": {
          "connection": "DP8K1crVkXUsP4X4:ins:in"
        },
        "RmOWxAygz9G6N8bE": {
          "connection": "DP8K1crVkXUsP4X4:ins:in"
        },
        "IcQwrW8ZGzP1stLO": {
          "connection": "DP8K1crVkXUsP4X4:ins:in"
        },
        "1UASRKGVk58cwcWL": {
          "connection": "DP8K1crVkXUsP4X4:ins:in"
        },
        "DU6ufqaw9NBgbQWI": {
          "connection": "DP8K1crVkXUsP4X4:ins:in"
        },
        "H1CROC76Yfjc7eJS": {
          "connection": "DP8K1crVkXUsP4X4:ins:in"
        },
        "prtafW7008OVaAo9": {
          "connection": "DP8K1crVkXUsP4X4:ins:in"
        }
      }
    },
    {
      "type": "file",
      "position": {
        "x": 2090.1944444444453,
        "y": -20.749999999999602
      },
      "id": "xURnbZ6s5Bay9jpz",
      "inputs": {
        "file": {
          "value": "jb2a.markers.horror.purple.02"
        },
        "effect": {
          "connection": "DIKQm9cpxx67j5yf:outputs:effect"
        }
      },
      "outs": {
        "out": {
          "connection": "3v5Py0kM4c1sAYDK:ins:in"
        }
      }
    },
    {
      "type": "file",
      "position": {
        "x": 2104.083333333334,
        "y": 231.33333333333394
      },
      "id": "DP8K1crVkXUsP4X4",
      "inputs": {
        "file": {
          "value": "jb2a.markers.horror.purple.01"
        },
        "effect": {
          "connection": "DIKQm9cpxx67j5yf:outputs:effect"
        }
      },
      "outs": {
        "out": {
          "connection": "3v5Py0kM4c1sAYDK:ins:in"
        }
      }
    }
  ],
  "name": "Frightened",
  "description": "<p>Written by @Chasarooni</p>",
  "folder": "Conditions",
  "id": "nMHLUByWH7ILKsJN"
}
